hca/__init__.py
hca/staging_area_validator.py
hca_import_validation-0.0.18.dist-info/licenses/LICENSE
hca_import_validation-0.0.18.dist-info/METADATA
hca_import_validation-0.0.18.dist-info/WHEEL
hca_import_validation-0.0.18.dist-info/top_level.txt
hca_import_validation-0.0.18.dist-info/RECORD
