Metadata-Version: 2.4
Name: hca-import-validation
Version: 0.0.18
Summary: HCA Staging Import Validation
Project-URL: Source, https://github.com/dataBiosphere/hca-import-validation
Classifier: Programming Language :: Python :: 3
Classifier: License :: OSI Approved :: Apache Software License
Classifier: Operating System :: OS Independent
Requires-Python: >=3.6
License-File: LICENSE
Requires-Dist: requests
Requires-Dist: google
Requires-Dist: google-cloud-core
Requires-Dist: google-cloud-storage
Requires-Dist: jsonschema
Requires-Dist: more-itertools
Requires-Dist: strict-rfc3339
Dynamic: license-file
